DESCRIPTION.rst
MANIFEST.in
README.md
setup.cfg
setup.py
api/__init__.py
api/control_services.py
api/network_services.py
api/nvp2.py
api/nvp_api.py
api/ovs.py
api/ovs_rmt.py
api/transport.py
automation/__init__.py
automation/nvpconfig.py
automation/transportnode.py
automation/configs/nvp-config-example.json
common/__init__.py
common/util/__init__.py
common/util/ssh.py
common/util/util.py
etc/nvp.conf
nvpnsxapi.egg-info/PKG-INFO
nvpnsxapi.egg-info/SOURCES.txt
nvpnsxapi.egg-info/dependency_links.txt
nvpnsxapi.egg-info/entry_points.txt
nvpnsxapi.egg-info/requires.txt
nvpnsxapi.egg-info/top_level.txt
test/__init__.py
test/example_api_usage.py