Metadata-Version: 1.1
Name: nvpnsxapi
Version: 0.1.2.dev1
Summary: An NSX / NVP API Binding for Python
Home-page: https://github.com/wallnerryan/nsxnvpapi
Author: Ryan Wallner
Author-email: wallnerryan@gmail.com
License: Apache 2.0
Keywords: nsx nvp api python
Platform: UNKNOWN
Classifier: Development Status :: 2 - Pre-Alpha
Classifier: Intended Audience :: Developers
Classifier: Topic :: Software Development :: Libraries :: Python Modules
Classifier: License :: OSI Approved :: Apache Software License
Classifier: Programming Language :: Python :: 2.6
Classifier: Programming Language :: Python :: 2.7
